asuds-0.2.dist-info/DESCRIPTION.rst
asuds-0.2.dist-info/METADATA
asuds-0.2.dist-info/RECORD
asuds-0.2.dist-info/WHEEL
asuds-0.2.dist-info/metadata.json
asuds-0.2.dist-info/top_level.txt
asuds-0.2.dist-info/zip-safe
suds/__init__.py
suds/__init__.pyo
suds/argparser.py
suds/argparser.pyo
suds/builder.py
suds/builder.pyo
suds/cache.py
suds/cache.pyo
suds/client.py
suds/client.pyo
suds/metrics.py
suds/metrics.pyo
suds/options.py
suds/options.pyo
suds/plugin.py
suds/plugin.pyo
suds/properties.py
suds/properties.pyo
suds/reader.py
suds/reader.pyo
suds/resolver.py
suds/resolver.pyo
suds/servicedefinition.py
suds/servicedefinition.pyo
suds/serviceproxy.py
suds/serviceproxy.pyo
suds/soaparray.py
suds/soaparray.pyo
suds/store.py
suds/store.pyo
suds/sudsobject.py
suds/sudsobject.pyo
suds/version.py
suds/version.pyo
suds/wsdl.py
suds/wsdl.pyo
suds/wsse.py
suds/wsse.pyo
suds/bindings/__init__.py
suds/bindings/__init__.pyo
suds/bindings/binding.py
suds/bindings/binding.pyo
suds/bindings/document.py
suds/bindings/document.pyo
suds/bindings/multiref.py
suds/bindings/multiref.pyo
suds/bindings/rpc.py
suds/bindings/rpc.pyo
suds/mx/__init__.py
suds/mx/__init__.pyo
suds/mx/appender.py
suds/mx/appender.pyo
suds/mx/basic.py
suds/mx/basic.pyo
suds/mx/core.py
suds/mx/core.pyo
suds/mx/encoded.py
suds/mx/encoded.pyo
suds/mx/literal.py
suds/mx/literal.pyo
suds/mx/typer.py
suds/mx/typer.pyo
suds/sax/__init__.py
suds/sax/__init__.pyo
suds/sax/attribute.py
suds/sax/attribute.pyo
suds/sax/date.py
suds/sax/date.pyo
suds/sax/document.py
suds/sax/document.pyo
suds/sax/element.py
suds/sax/element.pyo
suds/sax/enc.py
suds/sax/enc.pyo
suds/sax/parser.py
suds/sax/parser.pyo
suds/sax/text.py
suds/sax/text.pyo
suds/transport/__init__.py
suds/transport/__init__.pyo
suds/transport/http.py
suds/transport/http.pyo
suds/transport/https.py
suds/transport/https.pyo
suds/transport/options.py
suds/transport/options.pyo
suds/umx/__init__.py
suds/umx/__init__.pyo
suds/umx/attrlist.py
suds/umx/attrlist.pyo
suds/umx/basic.py
suds/umx/basic.pyo
suds/umx/core.py
suds/umx/core.pyo
suds/umx/encoded.py
suds/umx/encoded.pyo
