Metadata-Version: 1.1
Name: asuds
Version: 0.2
Summary: Lightweight SOAP client (Authentise's fork)
Home-page: http://bitbucket.org/Authentise/asuds
Author: Eli Ribble
Author-email: eli@authentise.com
License: UNKNOWN
Keywords: SOAP,web,service,client
Platform: UNKNOWN
Obsoletes: s
Obsoletes: u
Obsoletes: d
Obsoletes: s
